graphflow/__init__.py
graphflow/hits/__init__.py
graphflow/hits/hitsrank.py
graphflow/pagerank/GooglePageRank.py
graphflow/pagerank/__init__.py
graphflow/pagerank/cpagerank.c
graphflow/pagerank/cpagerank.cpython-312-darwin.so
graphflow/pagerank/cpagerank.pyx
graphflow/simvoltage/SocialNetworkSimVoltage.py
graphflow/simvoltage/__init__.py
graphflow/simvoltage/exceptions.py
graphflow/simvoltage/resistancedist.py
graphflow-0.7.1.dist-info/licenses/LICENSE
graphflow-0.7.1.dist-info/METADATA
graphflow-0.7.1.dist-info/WHEEL
graphflow-0.7.1.dist-info/top_level.txt
graphflow-0.7.1.dist-info/RECORD
