Metadata-Version: 2.4
Name: graphflow
Version: 0.7.1
Summary: Algorithms for Graph Flow Analysis
Author-email: Kwan Yuet Stephen Ho <stephenhky@yahoo.com.hk>
License: MIT
Project-URL: Repository, https://github.com/stephenhky/GraphFlow
Project-URL: Issues, https://github.com/stephenhky/GraphFlow/issues
Project-URL: Documentation, https://graphflow.readthedocs.io
Keywords: network,graph
Classifier: Topic :: Scientific/Engineering :: Artificial Intelligence
Classifier: Topic :: Scientific/Engineering :: Mathematics
Classifier: Topic :: Software Development :: Libraries :: Python Modules
Classifier: Programming Language :: Python :: 3.9
Classifier: Programming Language :: Python :: 3.10
Classifier: Programming Language :: Python :: 3.11
Classifier: Programming Language :: Python :: 3.12
Classifier: Programming Language :: Python :: 3.13
Classifier: Programming Language :: Cython
Classifier: Programming Language :: C
Classifier: License :: OSI Approved :: MIT License
Requires-Python: >=3.9
License-File: LICENSE
Requires-Dist: Cython>=0.29.0
Requires-Dist: numpy>=1.20.0
Requires-Dist: networkx>=3.0
Requires-Dist: sparse>=0.10.0
Provides-Extra: test
Requires-Dist: unittest2; extra == "test"
Requires-Dist: pytest; extra == "test"
Requires-Dist: pytest-cython; extra == "test"
Requires-Dist: pandas; extra == "test"
Requires-Dist: scipy; extra == "test"
Dynamic: license-file
